cloudrecon/__init__.py
cloudrecon/__main__.py
cloudrecon/cloudrecon.py
cloudrecon/cloudrecon.yml
cloudrecon/constants.py
cloudrecon/mongodb.py
cloudrecon-0.2.5.dist-info/LICENSE
cloudrecon-0.2.5.dist-info/METADATA
cloudrecon-0.2.5.dist-info/WHEEL
cloudrecon-0.2.5.dist-info/entry_points.txt
cloudrecon-0.2.5.dist-info/top_level.txt
cloudrecon-0.2.5.dist-info/RECORD
