Metadata-Version: 2.1
Name: cloudrecon
Version: 0.2.5
Summary: Cloud bucket/blob finder.
Home-page: https://github.com/3of3/cloudrecon
Author: Nathaniel 'Q' Quist
Author-email: qcuequeue@gmail.com
License: UNKNOWN
Platform: UNKNOWN
Classifier: Programming Language :: Python :: 3
Classifier: Programming Language :: Python :: 3.6
Classifier: Programming Language :: Python :: 3.7
Classifier: Programming Language :: Python :: 3.8
Classifier: License :: OSI Approved :: MIT License
Classifier: Operating System :: OS Independent
Requires-Python: >=3.6
Requires-Dist: mergedeep (>=1.1)
Requires-Dist: requests (>=2.23)
Requires-Dist: pymongo (>=3.10)
Requires-Dist: pyyaml (>=5.3)
